examples/blur-image/model.py
examples/dummy/model.py
examples/rotate-image/model.py
examples/stable-diffusion/model.py
examples/stable-diffusion/test.py
examples/stable-diffusion-xl/model.py
kservehelper/__init__.py
kservehelper/cache.py
kservehelper/cli.py
kservehelper/docker.py
kservehelper/model.py
kservehelper/storage.py
kservehelper/types.py
kservehelper/utils.py
kservehelper/kserve/__init__.py
kservehelper/kserve/model_server.py
kservehelper/kserve/rest/__init__.py
kservehelper/kserve/rest/server.py
kservehelper/kserve/rest/v1_endpoints.py
tests/test_batch_inputs.py
tests/test_cache.py
tests/test_model_cache.py
tests/test_predict.py
tests/test_s3.py
tests/test_transform.py
tests/test_upload.py
kservehelper-2.0.0.dist-info/METADATA
kservehelper-2.0.0.dist-info/WHEEL
kservehelper-2.0.0.dist-info/entry_points.txt
kservehelper-2.0.0.dist-info/top_level.txt
kservehelper-2.0.0.dist-info/RECORD
