Metadata-Version: 2.1
Name: kservehelper
Version: 2.0.0
Summary: A KServe Model Wrapper
Home-page: https://github.com/yangwenz/kserve-helper
Author: Wenzhuo Yang
License: 3-Clause BSD
Requires-Python: >=3.8,<4
Requires-Dist: pydantic ==2.8.2
Requires-Dist: kserve ==0.13.1
Requires-Dist: requests ==2.29.0
Requires-Dist: aiohttp ==3.8.3
Requires-Dist: aiofiles ==23.2.1
Requires-Dist: schema
Requires-Dist: pyyaml
Requires-Dist: click
Requires-Dist: pytest
Requires-Dist: mmh3
Requires-Dist: boto3
